{
	"title": "Sierpień 2010",
	"filename": "sierpien-2010",
	"date": "2010-08",
	"songs": [
		{
			"artist": "diary of dreams",
			"title": "bladerunner 2001"
		},
		{
			"artist": "the sisters of mercy",
			"title": "this corrosion"
		},
		{
			"artist": "the beauty of gemina",
			"title": "obscura"
		},
		{
			"artist": "front line assembly",
			"title": "afterlife (pk)"
		},
		{
			"artist": "leaether strip",
			"title": "song for pia"
		},
		{
			"artist": "the twilight garden",
			"title": "dead adults"
		},
		{
			"artist": "the twilight garden",
			"title": "a world we pretend"
		},
		{
			"artist": "lisa gerrard, marcello de francisci",
			"title": "diary for the fallen"
		},
		{
			"artist": "lisa gerrard, marcello de francisci",
			"title": "departum"
		},
		{
			"artist": "lisa gerrard, marcello de francisci",
			"title": "cor nobilis"
		},
		{
			"artist": "lisa gerrard, marcello de francisci",
			"title": "the gentle ones"
		},
		{
			"artist": "brendan perry",
			"title": "crecent"
		},
		{
			"artist": "the beauty of gemina",
			"title": "in your eyes"
		},
		{
			"artist": "the beauty of gemina",
			"title": "dark rain"
		},
		{
			"artist": "the beauty of gemina",
			"title": "end of all"
		},
		{
			"artist": "the beauty of gemina",
			"title": "rumours"
		},
		{
			"artist": "the beauty of gemina",
			"title": "suicide landscape"
		},
		{
			"artist": "the beauty of gemina",
			"title": "a fortune tellers dream"
		},
		{
			"artist": "the beauty of gemina",
			"title": "victims of love (qui tollis)"
		},
		{
			"artist": "front line assembly",
			"title": "afterlife (pk)"
		},
		{
			"artist": "digital angel",
			"title": "not the first"
		},
		{
			"artist": "digital angel",
			"title": "winter"
		},
		{
			"artist": "digital angel",
			"title": "again"
		},
		{
			"artist": "in strict confidence",
			"title": "set me free"
		},
		{
			"artist": "in strict confidence",
			"title": "i surrander"
		},
		{
			"artist": "whispers in the shadow",
			"title": "clouds without water"
		},
		{
			"artist": "whispers in the shadow",
			"title": "blessed in disguise"
		},
		{
			"artist": "whispers in the shadow",
			"title": "the eternal arcane"
		},
		{
			"artist": "fjernlys",
			"title": "beyond the north"
		},
		{
			"artist": "fjernlys",
			"title": "star`s orbit"
		},
		{
			"artist": "fjernlys",
			"title": "silence"
		},
		{
			"artist": "front line assembly",
			"title": "afterlife (pk)"
		},
		{
			"artist": "conjure one",
			"title": "i dream in colour"
		},
		{
			"artist": "in my rosary",
			"title": "no doubt"
		},
		{
			"artist": "in my rosary",
			"title": "the rose of the world"
		},
		{
			"artist": "in my rosary",
			"title": "ghost"
		},
		{
			"artist": "in my rosary",
			"title": "the liar"
		},
		{
			"artist": "in my rosary",
			"title": "dust"
		},
		{
			"artist": "in my rosary",
			"title": "sleepless"
		},
		{
			"artist": "in my rosary",
			"title": "night owl`97"
		},
		{
			"artist": "in my rosary",
			"title": "three nails"
		},
		{
			"artist": "in my rosary",
			"title": "ruler of my mind"
		},
		{
			"artist": "in my rosary",
			"title": "to an absent friend"
		},
		{
			"artist": "in my rosary",
			"title": "all we have"
		},
		{
			"artist": "in my rosary",
			"title": "to end"
		},
		{
			"artist": "in my rosary",
			"title": "fall apart"
		},
		{
			"artist": "in my rosary",
			"title": "farewellfront"
		},
		{
			"artist": "line assembly",
			"title": "afterlife (pk)"
		},
		{
			"artist": "wolfsheim",
			"title": "love is strange"
		},
		{
			"artist": "la floa maldita",
			"title": "voyaga"
		},
		{
			"artist": "paralysed age",
			"title": "self control"
		},
		{
			"artist": "zeromancer",
			"title": "send me an angel"
		},
		{
			"artist": "the gallery",
			"title": "the sun always shines on t.v."
		},
		{
			"artist": "daimonion",
			"title": "here comes the rain again"
		},
		{
			"artist": "paradise lost",
			"title": "small town boy"
		},
		{
			"artist": "kirlian camera",
			"title": "the final countdown"
		}
	]
}
