[
    {
        "artist": "diary of dreams",
        "title": "bladerunner 2001"
    },
    {
        "artist": "lisa gerrard",
        "title": "space weaver"
    },
    {
        "artist": "two moons",
        "title": "never more"
    },
    {
        "artist": "lebanon hanover",
        "title": "hard drug"
    },
    {
        "artist": "the colours of silence",
        "title": "a light in the dark"
    },
    {
        "artist": "black swan lane",
        "title": "the prisoner"
    },
    {
        "artist": "deleyaman",
        "title": "keep the light"
    },
    {
        "artist": "two moons",
        "title": "love is"
    },
    {
        "artist": "two moons",
        "title": "this is a fire"
    },
    {
        "artist": "schrodinger",
        "title": "bloody eyes"
    },
    {
        "artist": "schrodinger",
        "title": "fallen"
    },
    {
        "artist": "schrodinger",
        "title": "last night"
    },
    {
        "artist": "bootblacks",
        "title": "new lines"
    },
    {
        "artist": "seasurfer",
        "title": "too wild"
    },
    {
        "artist": "seasurfer",
        "title": "secrets"
    },
    {
        "artist": "seasurfer",
        "title": "shine"
    },
    {
        "artist": "lebanon hanover",
        "title": "hard drug"
    },
    {
        "artist": "black nail cabaret",
        "title": "my casual god"
    },
    {
        "artist": "astari nite",
        "title": "gloomy witch"
    },
    {
        "artist": "white door",
        "title": "among the mountains"
    },
    {
        "artist": "akli",
        "title": "robot"
    },
    {
        "artist": "sad",
        "title": "sign from above"
    },
    {
        "artist": "sad",
        "title": "raining pleasure"
    },
    {
        "artist": "seatemples",
        "title": "beagle #185"
    },
    {
        "artist": "morthem vlade art",
        "title": "heartache"
    },
    {
        "artist": "deine lakaien",
        "title": "because the night"
    },
    {
        "artist": "jackson vanhorn",
        "title": "sunday"
    },
    {
        "artist": "subhheim",
        "title": "ghosts"
    },
    {
        "artist": "agent side grinder",
        "title": "decompression (delphine coma remix)"
    },
    {
        "artist": "nnhmn",
        "title": "hypocrisy"
    },
    {
        "artist": "rue oberkampf",
        "title": "negativraum"
    },
    {
        "artist": "renard",
        "title": "intelligent design"
    },
    {
        "artist": "subheim",
        "title": "crimson"
    },
    {
        "artist": "lebanon hanover",
        "title": "hard drug"
    },
    {
        "artist": "crying vessel",
        "title": "the abyss"
    },
    {
        "artist": "blind delon",
        "title": "mourir seul"
    },
    {
        "artist": "remission international",
        "title": "tos2020 (trentemoller remix)"
    },
    {
        "artist": "the wake",
        "title": "figurine"
    },
    {
        "artist": "the wake",
        "title": "marry me"
    },
    {
        "artist": "blessing in disguise",
        "title": "here comes the rain again"
    },
    {
        "artist": "paradise lost",
        "title": "small town boy"
    },
    {
        "artist": "zeromancer",
        "title": "send me an angel"
    },
    {
        "artist": "the cascades",
        "title": "blue monday"
    },
    {
        "artist": "death loves veronica",
        "title": "winter never comes"
    }
]
